code_battles_cli/__init__.py
code_battles_cli/__main__.py
code_battles_cli/api.py
code_battles_cli/cli.py
code_battles_cli/log.py
code_battles_cli/commands/__init__.py
code_battles_cli/commands/download.py
code_battles_cli/commands/run.py
code_battles_cli/commands/upload.py
code_battles_cli-1.2.2.dist-info/METADATA
code_battles_cli-1.2.2.dist-info/WHEEL
code_battles_cli-1.2.2.dist-info/entry_points.txt
code_battles_cli-1.2.2.dist-info/licenses/LICENSE.md
code_battles_cli-1.2.2.dist-info/RECORD
