Metadata-Version: 2.3
Name: code-battles-cli
Version: 1.2.2
Summary: A CLI for competitors in any Code Battles event!
Requires-Python: >=3.8
Requires-Dist: click>=8.1.7
Requires-Dist: google-cloud-firestore>=2.19.0
Requires-Dist: requests>=2.32.3
Requires-Dist: rich>=13.9.3
